Metadata-Version: 2.1
Name: django-bootstrap-feedback-form
Version: 1.0.1
Summary: A Django app to to create a responsive bootstrap-styled email-driven feedback form with a captcha and an email confirmation feature.
Home-page: https://github.com/ksmvrheee/django-bootstrap-feedback-form
Author: Daniil Prokopov
Author-email: scbeeeop@ya.ru
License: MIT License
Classifier: Environment :: Web Environment
Classifier: Framework :: Django
Classifier: Framework :: Django :: 5.2
Classifier: Intended Audience :: Developers
Classifier: License :: OSI Approved :: MIT License
Classifier: Operating System :: OS Independent
Classifier: Programming Language :: Python
Classifier: Programming Language :: Python :: 3
Classifier: Programming Language :: Python :: 3 :: Only
Classifier: Programming Language :: Python :: 3.10
Classifier: Programming Language :: Python :: 3.11
Classifier: Programming Language :: Python :: 3.12
Classifier: Topic :: Internet :: WWW/HTTP
Classifier: Topic :: Internet :: WWW/HTTP :: Dynamic Content
Requires-Python: >=3.10
License-File: LICENSE
Requires-Dist: Django>=4.2
Requires-Dist: djangorestframework<4.0,>=3.15.2
Requires-Dist: requests<3.0,>=2.30.0
